{
  "PackageData": [
    {
      "Row": [
        {
          "SchemaColumnUId": "ae0e45ca-c495-4fe7-a39d-3ab7278e1617",
          "ColumnName": "Id",
          "Value": "439a422d-43a9-4831-b963-8d60d83b9791"
        },
        {
          "SchemaColumnUId": "736c30a7-c0ec-4fa9-b034-2552b319b633",
          "ColumnName": "Name",
          "Value": "House"
        }
      ]
    },
    {
      "Row": [
        {
          "SchemaColumnUId": "ae0e45ca-c495-4fe7-a39d-3ab7278e1617",
          "ColumnName": "Id",
          "Value": "610ec1d1-8de3-4825-8dc6-f82371a3037c"
        },
        {
          "SchemaColumnUId": "736c30a7-c0ec-4fa9-b034-2552b319b633",
          "ColumnName": "Name",
          "Value": "Office space"
        }
      ]
    },
    {
      "Row": [
        {
          "SchemaColumnUId": "ae0e45ca-c495-4fe7-a39d-3ab7278e1617",
          "ColumnName": "Id",
          "Value": "6d11f220-e4a4-498d-89ba-d4eba9f0f6c1"
        },
        {
          "SchemaColumnUId": "736c30a7-c0ec-4fa9-b034-2552b319b633",
          "ColumnName": "Name",
          "Value": "Apartment"
        }
      ]
    },
    {
      "Row": [
        {
          "SchemaColumnUId": "ae0e45ca-c495-4fe7-a39d-3ab7278e1617",
          "ColumnName": "Id",
          "Value": "fe0a6ca6-32da-4b0b-a0b3-9879354c2be2"
        },
        {
          "SchemaColumnUId": "736c30a7-c0ec-4fa9-b034-2552b319b633",
          "ColumnName": "Name",
          "Value": "Parking area"
        }
      ]
    }
  ]
}